setup.py
redismock/__init__.py
redismock/lock.py
redismock/mockmanager.py
redismock/pipeline.py
redismock.egg-info/PKG-INFO
redismock.egg-info/SOURCES.txt
redismock.egg-info/dependency_links.txt
redismock.egg-info/top_level.txt