Metadata-Version: 1.0
Name: redismock
Version: 1.0.5
Summary: Mock for redis-py
Home-page: https://github.com/HackingHabits/mockredis
Author: UNKNOWN
Author-email: UNKNOWN
License: Apache2
Platform: UNKNOWN
